fair_kmeans/__init__.py
fair_kmeans/_core.cpp
fair_kmeans/core.py
fair_kmeans/fair_clustering_tools.cpp
fair_kmeans/fair_clustering_tools.h
fair_kmeans/lemon/LICENSE
fair_kmeans/lemon/assert.h
fair_kmeans/lemon/bin_heap.h
fair_kmeans/lemon/bits/alteration_notifier.h
fair_kmeans/lemon/bits/array_map.h
fair_kmeans/lemon/bits/default_map.h
fair_kmeans/lemon/bits/enable_if.h
fair_kmeans/lemon/bits/graph_extender.h
fair_kmeans/lemon/bits/lock.h
fair_kmeans/lemon/bits/map_extender.h
fair_kmeans/lemon/bits/stl_iterators.h
fair_kmeans/lemon/bits/traits.h
fair_kmeans/lemon/bits/vector_map.h
fair_kmeans/lemon/capacity_scaling.h
fair_kmeans/lemon/concept_check.h
fair_kmeans/lemon/concepts/maps.h
fair_kmeans/lemon/config.h
fair_kmeans/lemon/core.h
fair_kmeans/lemon/error.h
fair_kmeans/lemon/maps.h
fair_kmeans/lemon/static_graph.h
fair_kmeans/point.cpp
fair_kmeans/point.h
fair_kmeans/util.py
fair_kmeans/_core.cpython-310-x86_64-linux-gnu.so
fair_kmeans-0.1.2.dist-info/LICENSE
fair_kmeans-0.1.2.dist-info/METADATA
fair_kmeans-0.1.2.dist-info/WHEEL
fair_kmeans-0.1.2.dist-info/RECORD
