Metadata-Version: 2.1
Name: fair-kmeans
Version: 0.1.2
Summary: Fair K-Means produces a fair clustering assignment according to the fairness definition of Chierichetti et al. Each point has a binary color, and the goal is to assign the points to clusters such that the number of points with different colors in each cluster is the same and the cost of the clusters is minimized.
License: LICENSE
Author: Melanie Schmidt
Author-email: mschmidt@hhu.de
Requires-Python: >=3.9,<4.0
Classifier: License :: Other/Proprietary License
Classifier: Programming Language :: Python :: 3
Classifier: Programming Language :: Python :: 3.9
Classifier: Programming Language :: Python :: 3.10
Classifier: Programming Language :: Python :: 3.11
Classifier: Programming Language :: Python :: 3.12
Requires-Dist: numpy (>=1.26.4,<2.0.0)
Requires-Dist: scikit-learn (>=1.6.1,<2.0.0)
